{
  "appointment": [
    {
      "Id": "APT001",
      "pName": "Denise Stevans",
      "address": "United States, San Francisco",
      "imglink": "http://localhost:4200/assets/img/patient13.jpg",
      "Age": 35,
      "dName": "Henry Daniels",
      "dep": "Cardiology",
      "date": "30 Dec 2018",
      "time": "10.00am-11.00am",
      "status": "true"
    },
    {
      "Id": "APT001",
      "pName": "Cristina Groves",
      "address": "United States, San Francisco",
      "imglink": "http://localhost:4200/assets/img/patient14.jpg",
      "Age": 35,
      "dName": "Henry Daniels",
      "dep": "Cardiology",
      "date": "30 Dec 2018",
      "time": "10.00am-11.00am",
      "status": "true"
    },
    {
      "Id": "APT001",
      "pName": "Marie Wells",
      "address": "United States, San Francisco",
      "imglink": "http://localhost:4200/assets/img/patient3.jpg",
      "Age": 35,
      "dName": "Henry Daniels",
      "dep": "Cardiology",
      "date": "30 Dec 2018",
      "time": "10.00am-11.00am",
      "status": true
    },
    {
      "Id": "APT001",
      "pName": "John Doe",
      "address": "United States, San Francisco",
      "imglink": "http://localhost:4200/assets/img/patient4.jpg",
      "Age": 35,
      "dName": "Henry Daniels",
      "dep": "Cardiology",
      "date": "30 Dec 2018",
      "time": "10.00am-11.00am",
      "status": true
    },
    {
      "Id": "APT001",
      "pName": "Hannah grace",
      "address": "United States, San Francisco",
      "imglink": "http://localhost:4200/assets/img/patient5.jpg",
      "Age": 35,
      "dName": "Henry Daniels",
      "dep": "Cardiology",
      "date": "30 Dec 2018",
      "time": "10.00am-11.00am",
      "status": true
    },
    {
      "Id": "APT001",
      "pName": "Wiliam straight",
      "address": "United States, San Francisco",
      "imglink": "http://localhost:4200/assets/img/patient6.jpg",
      "Age": 35,
      "dName": "Henry Daniels",
      "dep": "Cardiology",
      "date": "30 Dec 2018",
      "time": "10.00am-11.00am",
      "status": true
    },
    {
      "Id": "APT002",
      "pName": "Thomas Shelby",
      "address": "United States, San Francisco",
      "imglink": "http://localhost:4200/assets/img/patient7.jpg",
      "Age": 35,
      "dName": "Henry Daniels",
      "dep": "Cardiology",
      "date": "30 Dec 2018",
      "time": "10.00am-11.00am",
      "status": true,
      "id": 11
    },
    {
      "Id": "APT002",
      "pName": "Arthur jaundy",
      "address": "United States, San Francisco",
      "imglink": "http://localhost:4200/assets/img/patient8.jpg",
      "Age": 35,
      "dName": "Henry Daniels",
      "dep": "Cardiology",
      "date": "30 Dec 2018",
      "time": "10.00am-11.00am",
      "status": true,
      "id": 12
    },
    {
      "Id": "APT002",
      "pName": "Evans alphonso",
      "address": "United States, San Francisco",
      "imglink": "http://localhost:4200/assets/img/patient9.jpg",
      "Age": 35,
      "dName": "Henry Daniels",
      "dep": "Cardiology",
      "date": "30 Dec 2018",
      "time": "10.00am-11.00am",
      "status": true,
      "id": 13
    },
    {
      "Id": "APT002",
      "pName": "Aron Stevans",
      "address": "United States, San Francisco",
      "imglink": "http://localhost:4200/assets/img/patient11.jpg",
      "Age": 35,
      "dName": "Henry Daniels",
      "dep": "Cardiology",
      "date": "30 Dec 2018",
      "time": "10.00am-11.00am",
      "status": true,
      "id": 15
    },
    {
      "Id": "APT002",
      "pName": "Steve Jobs",
      "address": "United States, San Francisco",
      "imglink": "http://localhost:4200/assets/img/patient12.jpg",
      "Age": 35,
      "dName": "Henry Daniels",
      "dep": "Cardiology",
      "date": "30 Dec 2018",
      "time": "10.00am-11.00am",
      "status": true,
      "id": 16
    },
    {
      "Id": "ur",
      "pName": "erty",
      "dep": "fgh",
      "Age": "cvb",
      "date": "cvb",
      "time": "vbn",
      "email": "dfg",
      "phone": "vbn",
      "msg": "fghj",
      "id": 20
    }
  ],
  "Doctors": [
    {
      "img": "assets/img/doctor-thumb-07.jpg",
      "name": "Cristina Groves",
      "department": "Gynecologist",
      "add": "United States, San Francisco",
      "id": 1
    },
    {
      "img": "assets/img/doctor-thumb-04.jpg",
      "name": "Marie Wells",
      "department": "Psychiatrist",
      "add": "United States, San Francisco",
      "id": 2
    },
    {
      "img": "assets/img/doctor-thumb-04.jpg",
      "name": "Henry Daniels",
      "department": "Cardiologist",
      "add": "United States, San Francisco",
      "id": 3
    },
    {
      "img": "assets/img/doctor-thumb-11.jpg",
      "name": "Mark Hunter",
      "department": "Urologist",
      "add": "United States, San Francisco",
      "id": 4
    },
    {
      "img": "assets/img/doctor-thumb-03.jpg",
      "name": "Michael Sullivan",
      "department": "Ophthalmologist",
      "add": "United States, San Francisco",
      "id": 5
    },
    {
      "img": "assets/img/doctor-thumb-03.jpg",
      "name": "Linda Barrett",
      "department": "Dentist",
      "add": "United States, San Francisco",
      "id": 6
    },
    {
      "img": "assets/img/doctor-thumb-10.jpg",
      "name": "Ronald Jacobs",
      "department": "Oncologist",
      "add": "United States, San Francisco",
      "id": 7
    },
    {
      "img": "assets/img/doctor-thumb-10.jpg",
      "name": "Shirley Willis",
      "department": "Radiologist",
      "add": "United States, San Francisco",
      "id": 8
    },
    {
      "img": "assets/img/doctor-thumb-08.jpg",
      "name": "Shirley Willis",
      "department": "General Surgery",
      "add": "United States, San Francisco",
      "id": 9
    },
    {
      "img": "assets/img/doctor-thumb-03.jpg",
      "name": "Pamela Curtis",
      "department": "Pediatrics",
      "add": "United States, San Francisco",
      "id": 10
    }
  ],
  "Departments": [
    {
      "dname": "Opthalmology",
      "isActive": "true",
      "id": 3
    },
    {
      "dname": "Ent Department",
      "isActive": "true",
      "id": 4
    },
    {
      "dname": "we,mnfw",
      "desc": "dm ,mw",
      "isActive": "false",
      "id": 5
    },
    {
      "dname": "",
      "desc": "",
      "isActive": "",
      "id": 6
    },
    {
      "dname": "wdq",
      "desc": "dqs",
      "isActive": "true",
      "id": 7
    }
  ],
  "Patients": [
    {
      "fName": "gouri",
      "lName": "sanket",
      "Age": 24,
      "email": "xgxrrythdf",
      "address": "80/a",
      "phno": "1234567894",
      "gender": "female",
      "status": "Active",
      "id": 1
    },
    {
      "fName": "vaishali",
      "lName": "sanjay",
      "Age": 35,
      "address": "80/A",
      "phno": "5678904321",
      "email": "vaisahli@gmail.com",
      "id": 4
    },
    {
      "fName": "errfre",
      "lName": "ergrwg",
      "Age": 32,
      "address": "grqr",
      "phno": "4521369874",
      "email": "gourisan2001@gmail.com",
      "id": 5
    }
  ]
}